ai_install.py
ai_install-0.1.1.dist-info/LICENSE
ai_install-0.1.1.dist-info/METADATA
ai_install-0.1.1.dist-info/WHEEL
ai_install-0.1.1.dist-info/entry_points.txt
ai_install-0.1.1.dist-info/top_level.txt
ai_install-0.1.1.dist-info/RECORD
